{
  "updated_at": "2026-07-03T08:12:53.982316+00:00",
  "instruments": [
    {
      "date": "2026-07-03",
      "prev_date": "2026-07-02",
      "pv_value": 161.47455,
      "curr_open": 161.12324,
      "curr_high": 161.49972,
      "curr_low": 160.60117,
      "curr_close": 160.83414,
      "direction": "buy",
      "touched": true,
      "dist_from_open": 0.35131,
      "symbol": "USD/JPY",
      "label": "USD/JPY",
      "pip_size": 0.01,
      "dist_from_open_pips": 35.1
    },
    {
      "date": "2026-07-03",
      "prev_date": "2026-07-02",
      "pv_value": 1.14275,
      "curr_open": 1.14339,
      "curr_high": 1.14621,
      "curr_low": 1.14209,
      "curr_close": 1.1455,
      "direction": "sell",
      "touched": true,
      "dist_from_open": 0.00064,
      "symbol": "EUR/USD",
      "label": "EUR/USD",
      "pip_size": 0.0001,
      "dist_from_open_pips": 6.4
    },
    {
      "date": "2026-07-03",
      "prev_date": "2026-07-02",
      "pv_value": 1.33333,
      "curr_open": 1.33472,
      "curr_high": 1.33803,
      "curr_low": 1.33348,
      "curr_close": 1.33703,
      "direction": "sell",
      "touched": false,
      "dist_from_open": 0.00139,
      "symbol": "GBP/USD",
      "label": "GBP/USD",
      "pip_size": 0.0001,
      "dist_from_open_pips": 13.9
    },
    {
      "date": "2026-07-03",
      "prev_date": "2026-07-02",
      "pv_value": 184.39833,
      "curr_open": 184.22827,
      "curr_high": 184.58711,
      "curr_low": 184.05534,
      "curr_close": 184.21668,
      "direction": "buy",
      "touched": true,
      "dist_from_open": 0.17006,
      "symbol": "EUR/JPY",
      "label": "EUR/JPY",
      "pip_size": 0.01,
      "dist_from_open_pips": 17.0
    },
    {
      "date": "2026-07-03",
      "prev_date": "2026-07-02",
      "pv_value": 0.69165,
      "curr_open": 0.69226,
      "curr_high": 0.69493,
      "curr_low": 0.69116,
      "curr_close": 0.69448,
      "direction": "sell",
      "touched": true,
      "dist_from_open": 0.00061,
      "symbol": "AUD/USD",
      "label": "AUD/USD",
      "pip_size": 0.0001,
      "dist_from_open_pips": 6.1
    },
    {
      "date": "2026-07-03",
      "prev_date": "2026-07-02",
      "pv_value": 0.80486,
      "curr_open": 0.80351,
      "curr_high": 0.80472,
      "curr_low": 0.80112,
      "curr_close": 0.80205,
      "direction": "buy",
      "touched": false,
      "dist_from_open": 0.00135,
      "symbol": "USD/CHF",
      "label": "USD/CHF",
      "pip_size": 0.0001,
      "dist_from_open_pips": 13.5
    },
    {
      "date": "2026-07-03",
      "prev_date": "2026-07-02",
      "pv_value": 1.41861,
      "curr_open": 1.41815,
      "curr_high": 1.41985,
      "curr_low": 1.41588,
      "curr_close": 1.41785,
      "direction": "buy",
      "touched": true,
      "dist_from_open": 0.00046,
      "symbol": "USD/CAD",
      "label": "USD/CAD",
      "pip_size": 0.0001,
      "dist_from_open_pips": 4.6
    },
    {
      "date": "2026-07-03",
      "prev_date": "2026-07-02",
      "pv_value": 0.56947,
      "curr_open": 0.56988,
      "curr_high": 0.57269,
      "curr_low": 0.56901,
      "curr_close": 0.57214,
      "direction": "sell",
      "touched": true,
      "dist_from_open": 0.00041,
      "symbol": "NZD/USD",
      "label": "NZD/USD",
      "pip_size": 0.0001,
      "dist_from_open_pips": 4.1
    },
    {
      "date": "2026-07-03",
      "prev_date": "2026-07-02",
      "pv_value": 0.85719,
      "curr_open": 0.85665,
      "curr_high": 0.85727,
      "curr_low": 0.856,
      "curr_close": 0.85662,
      "direction": "buy",
      "touched": true,
      "dist_from_open": 0.00054,
      "symbol": "EUR/GBP",
      "label": "EUR/GBP",
      "pip_size": 0.0001,
      "dist_from_open_pips": 5.4
    },
    {
      "date": "2026-07-03",
      "prev_date": "2026-07-02",
      "pv_value": 0.92011,
      "curr_open": 0.91873,
      "curr_high": 0.91915,
      "curr_low": 0.91788,
      "curr_close": 0.91862,
      "direction": "buy",
      "touched": false,
      "dist_from_open": 0.00138,
      "symbol": "EUR/CHF",
      "label": "EUR/CHF",
      "pip_size": 0.0001,
      "dist_from_open_pips": 13.8
    },
    {
      "date": "2026-07-03",
      "prev_date": "2026-07-02",
      "pv_value": 4098.40877,
      "curr_open": 4123.72424,
      "curr_high": 4195.33479,
      "curr_low": 4120.90817,
      "curr_close": 4181.79617,
      "direction": "sell",
      "touched": false,
      "dist_from_open": 25.31547,
      "symbol": "XAU/USD",
      "label": "GOLD (XAU/USD)",
      "pip_size": 0.01,
      "dist_from_open_pips": 2531.5
    }
  ],
  "errors": []
}